qoqo_for_braket/__init__.py
qoqo_for_braket/backend.py
qoqo_for_braket/post_processing.py
qoqo_for_braket/qoqo_hybrid_helper.py
qoqo_for_braket/queued_results.py
qoqo_for_braket/interface/__init__.py
qoqo_for_braket/interface/ionq_verbatim_interface.py
qoqo_for_braket/interface/iqm_verbatim_interface.py
qoqo_for_braket/interface/oqc_verbatim_interface.py
qoqo_for_braket/interface/rigetti_verbatim_interface.py
qoqo_for_braket-0.9.0.dist-info/METADATA
qoqo_for_braket-0.9.0.dist-info/WHEEL
qoqo_for_braket-0.9.0.dist-info/top_level.txt
qoqo_for_braket-0.9.0.dist-info/RECORD
