Metadata-Version: 2.4
Name: qoqo_for_braket
Version: 0.9.0
Author-email: HQS Quantum Simulation GmbH <info@quantumsimulations.de>
Maintainer-email: Kirsten Bark <kirsten.bark@quantumsimulations.de>
Requires-Python: >=3.10
Requires-Dist: pydantic
Requires-Dist: qoqo<2.0,>=1.21
Requires-Dist: qoqo_qasm>=0.15.2
Requires-Dist: amazon-braket-sdk>=1.5.9
Provides-Extra: tests
Requires-Dist: pytest-cov; extra == "tests"
Requires-Dist: pytest; extra == "tests"
Provides-Extra: dev
Requires-Dist: ruff; extra == "dev"
Requires-Dist: darglint; extra == "dev"
Requires-Dist: bandit; extra == "dev"
Requires-Dist: mypy; extra == "dev"
Requires-Dist: black; extra == "dev"
Provides-Extra: docs
Requires-Dist: sphinx>=2.1; extra == "docs"
Requires-Dist: nbsphinx; extra == "docs"
Requires-Dist: pygments; extra == "docs"
Requires-Dist: recommonmark; extra == "docs"
Requires-Dist: myst_parser; extra == "docs"
Requires-Dist: sphinx_rtd_theme; extra == "docs"
Requires-Dist: tomli; extra == "docs"
